quickentity.py
quickentity-0.0.1.dist-info/METADATA
quickentity-0.0.1.dist-info/WHEEL
quickentity-0.0.1.dist-info/licenses/LICENSE
quickentity-0.0.1.dist-info/RECORD
