Metadata-Version: 2.1
Name: QuickEntity
Version: 0.0.1
Summary: A library to train Named Entity Recognition on Spacy-based easily and quickly.
Project-URL: Homepage, https://github.com/kissabi/quickentity
Project-URL: Bug Tracker, https://github.com/kissabi/quickentity/issues
Author-email: Kayenga Campos <kayengacampos@gmail.com>
License-File: LICENSE
Classifier: License :: OSI Approved :: MIT License
Classifier: Operating System :: OS Independent
Classifier: Programming Language :: Python :: 3
Requires-Python: >=3.7
Requires-Dist: nltk>=3.7
Requires-Dist: spacy>=3.4.4
